LICENSE.md
MANIFEST.in
README.md
setup.py
django_tasks_manager.egg-info/PKG-INFO
django_tasks_manager.egg-info/SOURCES.txt
django_tasks_manager.egg-info/dependency_links.txt
django_tasks_manager.egg-info/not-zip-safe
django_tasks_manager.egg-info/requires.txt
django_tasks_manager.egg-info/top_level.txt
django_tm/__init__.py
django_tm/admin.py
django_tm/apps.py
django_tm/celery.py
django_tm/config.py
django_tm/models.py
django_tm/signals.py
django_tm/tasks.py
django_tm/tests.py
django_tm/urls.py
django_tm/views.py
django_tm/celery_logs/.gitignore
django_tm/celery_scripts/check-db-health.py
django_tm/celery_scripts/check-disk-free.py
django_tm/celery_scripts/clean-database.py
django_tm/migrations/__init__.py
django_tm/templates/static/.gitkeep
django_tm/templates/tasks/base.html
django_tm/templates/tasks/index.html
django_tm/templatetags/__init__.py
django_tm/templatetags/formats.py
docs/blank.txt